autoipaalign/__init__.py
autoipaalign/core/__init__.py
autoipaalign/core/cli.py
autoipaalign/core/speech_recognition.py
autoipaalign/core/textgrid_io.py
autoipaalign/web/__init__.py
autoipaalign/web/app.py
autoipaalign-1.0.1.dist-info/WHEEL
autoipaalign-1.0.1.dist-info/entry_points.txt
autoipaalign-1.0.1.dist-info/METADATA
autoipaalign-1.0.1.dist-info/RECORD
