Metadata-Version: 2.3
Name: autoipaalign
Version: 1.0.1
Summary: Automatic IPA alignment workspace with CLI, comparison tools, and web interface
Requires-Dist: transformers[torch]
Requires-Dist: librosa
Requires-Dist: tgt
Requires-Dist: soundfile
Requires-Dist: tyro
Requires-Dist: openai-whisper ; extra == 'compare'
Requires-Dist: gradio==5.29.0 ; extra == 'web'
Requires-Python: >=3.10, <3.14
Provides-Extra: compare
Provides-Extra: web
